ocicoeaidpml/__init__.py
ocicoeaidpml/core.py
ocicoeaidpml-0.1.5.dist-info/METADATA
ocicoeaidpml-0.1.5.dist-info/WHEEL
ocicoeaidpml-0.1.5.dist-info/top_level.txt
ocicoeaidpml-0.1.5.dist-info/RECORD
