Metadata-Version: 2.4
Name: ocicoeaidpml
Version: 0.1.5
Summary: Spark schema analysis & ML use-case suggestion tool using OCI LLM
Home-page: https://github.com/yourusername/coeaidpml
Author: Your Name
Author-email: Nikesh Gogia <nikesh.g.gogia@oracle.com>
License: Oracle COE JAPAC
Project-URL: Homepage, https://github.com/yourusername/coeaidpml
Keywords: spark,llm,machine-learning,schema-analysis,oci
Requires-Python: >=3.11
Dynamic: author
Dynamic: home-page
Dynamic: requires-python
